a2/__init__.py
a2/data/__init__.py
a2/data/emoji/__init__.py
a2/data/emoji/emoji_df.csv
a2/data/vocabularies/__init__.py
a2/data/vocabularies/weather_vocab_enchanted_learning_com.txt
a2/data/vocabularies/weather_vocab_enchanted_precipitation.txt
a2/dataset/__init__.py
a2/dataset/emojis.py
a2/dataset/load_dataset.py
a2/dataset/radar.py
a2/dataset/stations.py
a2/dataset/tweets.py
a2/dataset/units.py
a2/dataset/utils_dataset.py
a2/plotting/__init__.py
a2/plotting/analysis.py
a2/plotting/axes_utils.py
a2/plotting/colormesh.py
a2/plotting/figures.py
a2/plotting/histogram_2d_utils.py
a2/plotting/histograms.py
a2/plotting/parallel_plotting.py
a2/plotting/timeseries.py
a2/plotting/utils_plotting.py
a2/plotting/weather_maps.py
a2/preprocess/__init__.py
a2/preprocess/embedding.py
a2/preprocess/normalize_text.py
a2/training/__init__.py
a2/training/benchmarks.py
a2/training/dataset_hugging.py
a2/training/evaluate_hugging.py
a2/training/model_configs.py
a2/training/model_infos.py
a2/training/tracking.py
a2/training/tracking_hugging.py
a2/training/training_deep500.py
a2/training/training_hugging.py
a2/training/training_performance.py
a2/training/utils_training.py
a2/twitter/__init__.py
a2/twitter/downloader.py
a2/twitter/locations.py
a2/twitter/twitter_api.py
a2/utils/__init__.py
a2/utils/argparse.py
a2/utils/checks.py
a2/utils/constants.py
a2/utils/file_handling.py
a2/utils/strings.py
a2/utils/testing.py
a2/utils/times.py
a2/utils/utils.py
a2-0.10.13.dist-info/METADATA
a2-0.10.13.dist-info/WHEEL
a2-0.10.13.dist-info/entry_points.txt
a2-0.10.13.dist-info/RECORD
